{"nodes": [{"id": "d_jed_documents_job_projects_glaux_app_dashboard_components_create_project_dialog_tsx", "label": "create-project-dialog.tsx", "file_type": "code", "source_file": "D:\\Jed\\Documents\\Job\\Projects\\glaux\\app\\dashboard\\components\\create-project-dialog.tsx", "source_location": "L1"}, {"id": "components_create_project_dialog_resetandclose", "label": "resetAndClose()", "file_type": "code", "source_file": "D:\\Jed\\Documents\\Job\\Projects\\glaux\\app\\dashboard\\components\\create-project-dialog.tsx", "source_location": "L31"}, {"id": "components_create_project_dialog_handlesubmit", "label": "handleSubmit()", "file_type": "code", "source_file": "D:\\Jed\\Documents\\Job\\Projects\\glaux\\app\\dashboard\\components\\create-project-dialog.tsx", "source_location": "L37"}], "edges": [{"source": "d_jed_documents_job_projects_glaux_app_dashboard_components_create_project_dialog_tsx", "target": "react", "relation": "imports_from", "confidence": "EXTRACTED", "source_file": "D:\\Jed\\Documents\\Job\\Projects\\glaux\\app\\dashboard\\components\\create-project-dialog.tsx", "source_location": "L3", "weight": 1.0}, {"source": "d_jed_documents_job_projects_glaux_app_dashboard_components_create_project_dialog_tsx", "target": "react_dom", "relation": "imports_from", "confidence": "EXTRACTED", "source_file": "D:\\Jed\\Documents\\Job\\Projects\\glaux\\app\\dashboard\\components\\create-project-dialog.tsx", "source_location": "L4", "weight": 1.0}, {"source": "d_jed_documents_job_projects_glaux_app_dashboard_components_create_project_dialog_tsx", "target": "framer_motion", "relation": "imports_from", "confidence": "EXTRACTED", "source_file": "D:\\Jed\\Documents\\Job\\Projects\\glaux\\app\\dashboard\\components\\create-project-dialog.tsx", "source_location": "L5", "weight": 1.0}, {"source": "d_jed_documents_job_projects_glaux_app_dashboard_components_create_project_dialog_tsx", "target": "lucide_react", "relation": "imports_from", "confidence": "EXTRACTED", "source_file": "D:\\Jed\\Documents\\Job\\Projects\\glaux\\app\\dashboard\\components\\create-project-dialog.tsx", "source_location": "L6", "weight": 1.0}, {"source": "d_jed_documents_job_projects_glaux_app_dashboard_components_create_project_dialog_tsx", "target": "d_jed_documents_job_projects_glaux_lib_utils", "relation": "imports_from", "confidence": "EXTRACTED", "source_file": "D:\\Jed\\Documents\\Job\\Projects\\glaux\\app\\dashboard\\components\\create-project-dialog.tsx", "source_location": "L7", "weight": 1.0}, {"source": "d_jed_documents_job_projects_glaux_app_dashboard_components_create_project_dialog_tsx", "target": "d_jed_documents_job_projects_glaux_lib_hooks_use_projects", "relation": "imports_from", "confidence": "EXTRACTED", "source_file": "D:\\Jed\\Documents\\Job\\Projects\\glaux\\app\\dashboard\\components\\create-project-dialog.tsx", "source_location": "L8", "weight": 1.0}, {"source": "d_jed_documents_job_projects_glaux_app_dashboard_components_create_project_dialog_tsx", "target": "d_jed_documents_job_projects_glaux_lib_schemas_project", "relation": "imports_from", "confidence": "EXTRACTED", "source_file": "D:\\Jed\\Documents\\Job\\Projects\\glaux\\app\\dashboard\\components\\create-project-dialog.tsx", "source_location": "L9", "weight": 1.0}, {"source": "d_jed_documents_job_projects_glaux_app_dashboard_components_create_project_dialog_tsx", "target": "d_jed_documents_job_projects_glaux_lib_schemas_project", "relation": "imports_from", "confidence": "EXTRACTED", "source_file": "D:\\Jed\\Documents\\Job\\Projects\\glaux\\app\\dashboard\\components\\create-project-dialog.tsx", "source_location": "L10", "weight": 1.0}, {"source": "d_jed_documents_job_projects_glaux_app_dashboard_components_create_project_dialog_tsx", "target": "components_create_project_dialog_resetandclose", "relation": "contains", "confidence": "EXTRACTED", "source_file": "D:\\Jed\\Documents\\Job\\Projects\\glaux\\app\\dashboard\\components\\create-project-dialog.tsx", "source_location": "L31", "weight": 1.0}, {"source": "d_jed_documents_job_projects_glaux_app_dashboard_components_create_project_dialog_tsx", "target": "components_create_project_dialog_handlesubmit", "relation": "contains", "confidence": "EXTRACTED", "source_file": "D:\\Jed\\Documents\\Job\\Projects\\glaux\\app\\dashboard\\components\\create-project-dialog.tsx", "source_location": "L37", "weight": 1.0}], "raw_calls": [{"caller_nid": "components_create_project_dialog_resetandclose", "callee": "setErrors", "source_file": "D:\\Jed\\Documents\\Job\\Projects\\glaux\\app\\dashboard\\components\\create-project-dialog.tsx", "source_location": "L32"}, {"caller_nid": "components_create_project_dialog_resetandclose", "callee": "reset", "source_file": "D:\\Jed\\Documents\\Job\\Projects\\glaux\\app\\dashboard\\components\\create-project-dialog.tsx", "source_location": "L33"}, {"caller_nid": "components_create_project_dialog_resetandclose", "callee": "onClose", "source_file": "D:\\Jed\\Documents\\Job\\Projects\\glaux\\app\\dashboard\\components\\create-project-dialog.tsx", "source_location": "L34"}, {"caller_nid": "components_create_project_dialog_handlesubmit", "callee": "preventDefault", "source_file": "D:\\Jed\\Documents\\Job\\Projects\\glaux\\app\\dashboard\\components\\create-project-dialog.tsx", "source_location": "L38"}, {"caller_nid": "components_create_project_dialog_handlesubmit", "callee": "setErrors", "source_file": "D:\\Jed\\Documents\\Job\\Projects\\glaux\\app\\dashboard\\components\\create-project-dialog.tsx", "source_location": "L39"}, {"caller_nid": "components_create_project_dialog_handlesubmit", "callee": "safeParse", "source_file": "D:\\Jed\\Documents\\Job\\Projects\\glaux\\app\\dashboard\\components\\create-project-dialog.tsx", "source_location": "L41"}, {"caller_nid": "components_create_project_dialog_handlesubmit", "callee": "setErrors", "source_file": "D:\\Jed\\Documents\\Job\\Projects\\glaux\\app\\dashboard\\components\\create-project-dialog.tsx", "source_location": "L48"}, {"caller_nid": "components_create_project_dialog_handlesubmit", "callee": "mutate", "source_file": "D:\\Jed\\Documents\\Job\\Projects\\glaux\\app\\dashboard\\components\\create-project-dialog.tsx", "source_location": "L52"}]}